selprotopy/__init__.py
selprotopy/commands.py
selprotopy/common.py
selprotopy/protoparser.py
selprotopy/telnetlib_support.py
selprotopy-0.1.dist-info/LICENSE
selprotopy-0.1.dist-info/METADATA
selprotopy-0.1.dist-info/WHEEL
selprotopy-0.1.dist-info/top_level.txt
selprotopy-0.1.dist-info/RECORD
