Metadata-Version: 2.1
Name: selprotopy
Version: 0.1
Summary: Schweitzer Engineering Laboratories (SEL) Protocol Bindings in Python
Home-page: https://github.com/engineerjoe440/selprotopy
Author: Joe Stanley
Author-email: joe_stanley@selinc.com
License: UNKNOWN
Project-URL: Source Repository, https://github.com/engineerjoe440/selprotopy
Project-URL: Bug Tracker, https://github.com/engineerjoe440/selprotopy/issues
Project-URL: Documentation, https://engineerjoe440.github.io/selprotopy/
Platform: UNKNOWN
Classifier: Programming Language :: Python :: 3
Classifier: License :: OSI Approved :: MIT License
Classifier: Operating System :: OS Independent
